{
	"events": [
		{
			"character": "character-1712756061.json",
			"event_id": "dialogic_001",
			"portrait": "",
			"text": "阁下是？是在敝舍前等待何人吗？"
		},
		{
			"character": "character-1713271590.json",
			"event_id": "dialogic_001",
			"portrait": "",
			"text": "朋友，请放心，我经商向来公平公正不亏待每一位客人。"
		},
		{
			"character": "character-1713271590.json",
			"event_id": "dialogic_001",
			"portrait": "",
			"text": "县里最近来了位官太爷巡视，那些芝麻官想好生招待这位大人，好攀上这层关系；"
		},
		{
			"character": "character-1713271590.json",
			"event_id": "dialogic_001",
			"portrait": "",
			"text": "于是委托我找你买一些野味"
		},
		{
			"character": "character-1713271590.json",
			"event_id": "dialogic_010",
			"options": [

			],
			"portrait": "",
			"question": "这几箱小小的礼品，不成敬意，还望赏我几分薄面。"
		},
		{
			"choice": "接受",
			"condition": "",
			"definition": "",
			"event_id": "dialogic_011",
			"value": ""
		},
		{
			"character": "character-1712756061.json",
			"event_id": "dialogic_001",
			"portrait": "",
			"text": "既然如此，我就当原因予你一份风水人情，毕竟相见是缘。"
		},
		{
			"character": "character-1713271590.json",
			"event_id": "dialogic_001",
			"portrait": "",
			"text": "有好友这句话，我还有什么可顾虑的？"
		},
		{
			"choice": "拒绝",
			"condition": "",
			"definition": "",
			"event_id": "dialogic_011",
			"value": ""
		},
		{
			"character": "character-1712756061.json",
			"event_id": "dialogic_001",
			"portrait": "",
			"text": "可惜我身居樊笼已久，逍遥半载，不为钱财动摇。"
		},
		{
			"character": "character-1713271590.json",
			"event_id": "dialogic_001",
			"portrait": "",
			"text": "岂是如此？朋友，是在下为那五斗米折腰，而需要你帮助我罢了，\n"
		},
		{
			"character": "character-1713271590.json",
			"event_id": "dialogic_001",
			"portrait": "",
			"text": "何况身处尘世，多一些钱财总不会是坏事，"
		},
		{
			"character": "character-1713271590.json",
			"event_id": "dialogic_001",
			"portrait": "",
			"text": "我们这些货商就搞这个吃饭了，还请朋友帮助我。"
		},
		{
			"character": "character-1712756061.json",
			"event_id": "dialogic_001",
			"portrait": "",
			"text": "也是，看你也是身不由己。那就助你吧。"
		},
		{
			"event_id": "dialogic_013"
		}
	],
	"metadata": {
		"dialogic-version": "1.5.1",
		"file": "timeline-1713272125.json",
		"name": "Start"
	}
}
